fastmorphops.cp310-win_amd64.pyd
fastmorph/__init__.py
fastmorph-1.8.0.dist-info/licenses/COPYING
fastmorph-1.8.0.dist-info/licenses/COPYING.LESSER
fastmorph-1.8.0.dist-info/METADATA
fastmorph-1.8.0.dist-info/WHEEL
fastmorph-1.8.0.dist-info/top_level.txt
fastmorph-1.8.0.dist-info/RECORD
