Metadata-Version: 2.4
Name: fastmorph
Version: 1.8.0
Summary: Morphological image processing for 3D multi-label images.
Home-page: https://github.com/seung-lab/fastmorph/
Author: William Silversmith
Author-email: ws9@princeton.edu
License: LGPL-3.0-or-later
Keywords: morphological dialate erode dilation erosion close open fill image processing
Classifier: Intended Audience :: Developers
Classifier: Development Status :: 4 - Beta
Classifier: Programming Language :: Python
Classifier: Programming Language :: Python :: 3
Classifier: Programming Language :: Python :: 3.9
Classifier: Programming Language :: Python :: 3.10
Classifier: Programming Language :: Python :: 3.11
Classifier: Programming Language :: Python :: 3.12
Classifier: Programming Language :: Python :: 3.13
Classifier: Topic :: Scientific/Engineering :: Image Processing
Classifier: Intended Audience :: Science/Research
Classifier: Operating System :: POSIX
Classifier: Operating System :: MacOS
Classifier: Operating System :: Microsoft :: Windows :: Windows 10
Requires-Python: >=3.9.0
License-File: COPYING
License-File: COPYING.LESSER
Requires-Dist: connected-components-3d
Requires-Dist: edt
Requires-Dist: fastremap
Requires-Dist: fill-voids
Requires-Dist: numpy
Requires-Dist: tqdm
Provides-Extra: spherical
Requires-Dist: scipy; extra == "spherical"
Dynamic: author
Dynamic: author-email
Dynamic: classifier
Dynamic: description
Dynamic: description-content-type
Dynamic: home-page
Dynamic: keywords
Dynamic: license
Dynamic: license-file
Dynamic: provides-extra
Dynamic: requires-dist
Dynamic: requires-python
Dynamic: summary
